metal/__init__.py
metal/cli.py
metal/commands/__init__.py
metal/commands/build.py
metal/commands/down.py
metal/commands/execute.py
metal/commands/install.py
metal/commands/ls.py
metal/commands/new.py
metal/commands/restart.py
metal/commands/shell.py
metal/commands/uninstall.py
metal/commands/up.py
metal/docker/docker-compose.base.yml
metal/docker/docker-compose.laravel.yml
metal/docker/docker-compose.rails.yml
metal/docker/laravel/Dockerfile
metal/docker/laravel/aliases.sh
metal/docker/laravel/php.ini
metal/docker/mysql/Dockerfile
metal/docker/mysql/metal.cnf
metal/docker/rails/Dockerfile
metal/docker/rails/aliases.sh
metal/lib/__init__.py
metal/lib/docker.py
metal/lib/project.py
metal/lib/runtime.py
metal/nginx/default.conf
metal/nginx/project.conf
metal_cli-0.0.2.dist-info/DESCRIPTION.rst
metal_cli-0.0.2.dist-info/METADATA
metal_cli-0.0.2.dist-info/RECORD
metal_cli-0.0.2.dist-info/WHEEL
metal_cli-0.0.2.dist-info/entry_points.txt
metal_cli-0.0.2.dist-info/metadata.json
metal_cli-0.0.2.dist-info/top_level.txt
